<?xml version="1.0"?>
<form string="Tree evolution" col="2">
    <notebook colspan="2">
        <page string="General" id="general">
            <label name="cycle"/>
            <field name="cycle"/>
            <label name="tree" />
            <field name="tree" />
            <label name="dbh1"/>
            <field name="dbh1"/>
            <label name="dbh2"/>
            <field name="dbh2"/>
            <label name="height"/>
            <field name="height"/>
            <label name="coppice"/>
            <field name="coppice"/>
            <label name="typo"/>
            <field name="typo" widget="selection"/>
            <label name="bark_stage"/>
            <field name="bark_stage" widget="selection"/>
            <label name="rot_stage"/>
            <field name="rot_stage" widget="selection"/>
            <notebook colspan="6">
                <page string="Observations" id="observations">
                    <field name="observation"/>
                </page>
                <page string="Ecological code" id="ecologie">
                    <field name="ecologie"/>
                </page>
            </notebook>
        </page>
    </notebook>
</form>
